[
    {
        "data": {
            "id": "0",
            "label": "0",
            "function": "nseq"
        },
        "position": {
            "x": 3635.1752500000002,
            "y": 14.3691815
        }
    },
    {
        "data": {
            "id": "1",
            "label": "1",
            "function": "nseq"
        },
        "position": {
            "x": 4258.4085,
            "y": 49.307865
        }
    },
    {
        "data": {
            "id": "2",
            "label": "2",
            "function": "nseq"
        },
        "position": {
            "x": 3200.78435,
            "y": 84.18695000000001
        }
    },
    {
        "data": {
            "id": "4",
            "label": "4",
            "function": "nseq"
        },
        "position": {
            "x": 3765.192,
            "y": 119.12564
        }
    },
    {
        "data": {
            "id": "5",
            "label": "5",
            "function": "nseq"
        },
        "position": {
            "x": 2913.7225,
            "y": 154.00473
        }
    },
    {
        "data": {
            "id": "3",
            "label": "3",
            "function": "nseq"
        },
        "position": {
            "x": 2894.114,
            "y": 188.9434
        }
    },
    {
        "data": {
            "id": "7",
            "label": "7",
            "function": "nseq"
        },
        "position": {
            "x": 2297.90835,
            "y": 223.82295
        }
    },
    {
        "data": {
            "id": "6",
            "label": "6",
            "function": "nseq"
        },
        "position": {
            "x": 4248.516,
            "y": 2981.8985
        }
    },
    {
        "data": {
            "id": "13",
            "label": "13",
            "function": "nseq"
        },
        "position": {
            "x": 2297.90835,
            "y": 258.761625
        }
    },
    {
        "data": {
            "id": "8",
            "label": "8",
            "function": "nseq"
        },
        "position": {
            "x": 2251.2719,
            "y": 363.518075
        }
    },
    {
        "data": {
            "id": "9",
            "label": "9",
            "function": "nseq"
        },
        "position": {
            "x": 1767.948,
            "y": 398.3972
        }
    },
    {
        "data": {
            "id": "10",
            "label": "10",
            "function": "nseq"
        },
        "position": {
            "x": 2084.5109,
            "y": 433.3363
        }
    },
    {
        "data": {
            "id": "11",
            "label": "11",
            "function": "nseq"
        },
        "position": {
            "x": 2084.5109,
            "y": 468.21540000000005
        }
    },
    {
        "data": {
            "id": "12",
            "label": "12",
            "function": "nseq"
        },
        "position": {
            "x": 1890.722,
            "y": 503.15405
        }
    },
    {
        "data": {
            "id": "14",
            "label": "14",
            "function": "nseq"
        },
        "position": {
            "x": 2484.4545000000003,
            "y": 538.03317
        }
    },
    {
        "data": {
            "id": "15",
            "label": "15",
            "function": "nseq"
        },
        "position": {
            "x": 2067.3755,
            "y": 572.97185
        }
    },
    {
        "data": {
            "id": "16",
            "label": "16",
            "function": "nseq"
        },
        "position": {
            "x": 1954.494,
            "y": 607.850925
        }
    },
    {
        "data": {
            "id": "17",
            "label": "17",
            "function": "nseq"
        },
        "position": {
            "x": 2052.5367499999998,
            "y": 642.79005
        }
    },
    {
        "data": {
            "id": "19",
            "label": "19",
            "function": "nseq"
        },
        "position": {
            "x": 2052.5367499999998,
            "y": 677.72875
        }
    },
    {
        "data": {
            "id": "21",
            "label": "21",
            "function": "nseq"
        },
        "position": {
            "x": 1880.8295,
            "y": 712.6078
        }
    },
    {
        "data": {
            "id": "24",
            "label": "24",
            "function": "nseq"
        },
        "position": {
            "x": 1610.97365,
            "y": 747.5465
        }
    },
    {
        "data": {
            "id": "25",
            "label": "25",
            "function": "nseq"
        },
        "position": {
            "x": 1387.719,
            "y": 782.42555
        }
    },
    {
        "data": {
            "id": "18",
            "label": "18",
            "function": "nseq"
        },
        "position": {
            "x": 1831.7199,
            "y": 817.36425
        }
    },
    {
        "data": {
            "id": "20",
            "label": "20",
            "function": "nseq"
        },
        "position": {
            "x": 1988.76485,
            "y": 852.2434
        }
    },
    {
        "data": {
            "id": "22",
            "label": "22",
            "function": "nseq"
        },
        "position": {
            "x": 1360.7262,
            "y": 887.1825
        }
    },
    {
        "data": {
            "id": "23",
            "label": "23",
            "function": "nseq"
        },
        "position": {
            "x": 1360.7262,
            "y": 922.0616
        }
    },
    {
        "data": {
            "id": "26",
            "label": "26",
            "function": "nseq"
        },
        "position": {
            "x": 1510.3872,
            "y": 957.0002499999999
        }
    },
    {
        "data": {
            "id": "28",
            "label": "28",
            "function": "nseq"
        },
        "position": {
            "x": 1027.04555,
            "y": 991.9389500000001
        }
    },
    {
        "data": {
            "id": "27",
            "label": "27",
            "function": "nseq"
        },
        "position": {
            "x": 1250.318,
            "y": 1026.818
        }
    },
    {
        "data": {
            "id": "29",
            "label": "29",
            "function": "nseq"
        },
        "position": {
            "x": 1029.5011,
            "y": 1061.7567
        }
    },
    {
        "data": {
            "id": "30",
            "label": "30",
            "function": "nseq"
        },
        "position": {
            "x": 1027.04555,
            "y": 1096.6363
        }
    },
    {
        "data": {
            "id": "31",
            "label": "31",
            "function": "nseq"
        },
        "position": {
            "x": 1139.90955,
            "y": 1131.57495
        }
    },
    {
        "data": {
            "id": "32",
            "label": "32",
            "function": "nseq"
        },
        "position": {
            "x": 916.6372,
            "y": 1166.454
        }
    },
    {
        "data": {
            "id": "33",
            "label": "33",
            "function": "nseq"
        },
        "position": {
            "x": 1073.6645,
            "y": 1201.3927
        }
    },
    {
        "data": {
            "id": "34",
            "label": "34",
            "function": "nseq"
        },
        "position": {
            "x": 970.6048000000001,
            "y": 1236.2718
        }
    },
    {
        "data": {
            "id": "35",
            "label": "35",
            "function": "nseq"
        },
        "position": {
            "x": 1181.6174,
            "y": 1271.21075
        }
    },
    {
        "data": {
            "id": "36",
            "label": "36",
            "function": "nseq"
        },
        "position": {
            "x": 1181.6174,
            "y": 1306.14935
        }
    },
    {
        "data": {
            "id": "37",
            "label": "37",
            "function": "nseq"
        },
        "position": {
            "x": 1404.8896499999998,
            "y": 1341.0285
        }
    },
    {
        "data": {
            "id": "38",
            "label": "38",
            "function": "nseq"
        },
        "position": {
            "x": 1404.8896499999998,
            "y": 1375.9674
        }
    },
    {
        "data": {
            "id": "39",
            "label": "39",
            "function": "nseq"
        },
        "position": {
            "x": 1750.8125,
            "y": 1410.8464000000001
        }
    },
    {
        "data": {
            "id": "41",
            "label": "41",
            "function": "nseq"
        },
        "position": {
            "x": 2241.5559,
            "y": 1445.78515
        }
    },
    {
        "data": {
            "id": "40",
            "label": "40",
            "function": "nseq"
        },
        "position": {
            "x": 2408.31675,
            "y": 1480.6644999999999
        }
    },
    {
        "data": {
            "id": "42",
            "label": "42",
            "function": "nseq"
        },
        "position": {
            "x": 2464.8458,
            "y": 1515.6032
        }
    },
    {
        "data": {
            "id": "43",
            "label": "43",
            "function": "nseq"
        },
        "position": {
            "x": 2204.81185,
            "y": 1550.4822
        }
    },
    {
        "data": {
            "id": "44",
            "label": "44",
            "function": "nseq"
        },
        "position": {
            "x": 2204.81185,
            "y": 1585.4211000000003
        }
    },
    {
        "data": {
            "id": "45",
            "label": "45",
            "function": "nseq"
        },
        "position": {
            "x": 1971.6294,
            "y": 1620.3598499999998
        }
    },
    {
        "data": {
            "id": "46",
            "label": "46",
            "function": "nseq"
        },
        "position": {
            "x": 1932.4122499999999,
            "y": 1655.2388500000002
        }
    },
    {
        "data": {
            "id": "51",
            "label": "51",
            "function": "nseq"
        },
        "position": {
            "x": 2162.9451,
            "y": 1690.17775
        }
    },
    {
        "data": {
            "id": "52",
            "label": "52",
            "function": "nseq"
        },
        "position": {
            "x": 1964.21,
            "y": 1725.0568999999998
        }
    },
    {
        "data": {
            "id": "59",
            "label": "59",
            "function": "nseq"
        },
        "position": {
            "x": 2101.64635,
            "y": 1759.99565
        }
    },
    {
        "data": {
            "id": "47",
            "label": "47",
            "function": "nseq"
        },
        "position": {
            "x": 1873.5866,
            "y": 1794.875
        }
    },
    {
        "data": {
            "id": "48",
            "label": "48",
            "function": "nseq"
        },
        "position": {
            "x": 1851.5049999999999,
            "y": 1829.8135
        }
    },
    {
        "data": {
            "id": "49",
            "label": "49",
            "function": "nseq"
        },
        "position": {
            "x": 2167.8914,
            "y": 1864.6926999999998
        }
    },
    {
        "data": {
            "id": "50",
            "label": "50",
            "function": "nseq"
        },
        "position": {
            "x": 1866.1672,
            "y": 1899.6316
        }
    },
    {
        "data": {
            "id": "53",
            "label": "53",
            "function": "nseq"
        },
        "position": {
            "x": 1858.7479,
            "y": 1934.5702
        }
    },
    {
        "data": {
            "id": "54",
            "label": "54",
            "function": "nseq"
        },
        "position": {
            "x": 2280.7729,
            "y": 1969.4493499999999
        }
    },
    {
        "data": {
            "id": "55",
            "label": "55",
            "function": "nseq"
        },
        "position": {
            "x": 2297.90835,
            "y": 2004.38825
        }
    },
    {
        "data": {
            "id": "56",
            "label": "56",
            "function": "nseq"
        },
        "position": {
            "x": 2427.9253,
            "y": 2039.2674
        }
    },
    {
        "data": {
            "id": "57",
            "label": "57",
            "function": "nseq"
        },
        "position": {
            "x": 2221.9473000000003,
            "y": 2074.206
        }
    },
    {
        "data": {
            "id": "58",
            "label": "58",
            "function": "nseq"
        },
        "position": {
            "x": 2221.9473000000003,
            "y": 2109.08515
        }
    },
    {
        "data": {
            "id": "63",
            "label": "63",
            "function": "nseq"
        },
        "position": {
            "x": 2275.82665,
            "y": 2912.0805
        }
    },
    {
        "data": {
            "id": "60",
            "label": "60",
            "function": "nseq"
        },
        "position": {
            "x": 1603.6248,
            "y": 2144.024
        }
    },
    {
        "data": {
            "id": "61",
            "label": "61",
            "function": "nseq"
        },
        "position": {
            "x": 1714.06865,
            "y": 2178.9030000000002
        }
    },
    {
        "data": {
            "id": "62",
            "label": "62",
            "function": "nseq"
        },
        "position": {
            "x": 1525.1024,
            "y": 2213.8418500000002
        }
    },
    {
        "data": {
            "id": "65",
            "label": "65",
            "function": "nseq"
        },
        "position": {
            "x": 1525.1024,
            "y": 2248.78075
        }
    },
    {
        "data": {
            "id": "66",
            "label": "66",
            "function": "nseq"
        },
        "position": {
            "x": 1586.4542000000001,
            "y": 2283.6599
        }
    },
    {
        "data": {
            "id": "67",
            "label": "67",
            "function": "nseq"
        },
        "position": {
            "x": 1483.39465,
            "y": 2318.5985
        }
    },
    {
        "data": {
            "id": "68",
            "label": "68",
            "function": "nseq"
        },
        "position": {
            "x": 1642.8772999999999,
            "y": 2353.4778
        }
    },
    {
        "data": {
            "id": "64",
            "label": "64",
            "function": "nseq"
        },
        "position": {
            "x": 1402.43425,
            "y": 2388.4165
        }
    },
    {
        "data": {
            "id": "69",
            "label": "69",
            "function": "nseq"
        },
        "position": {
            "x": 1549.6397000000002,
            "y": 2423.2955
        }
    },
    {
        "data": {
            "id": "71",
            "label": "71",
            "function": "nseq"
        },
        "position": {
            "x": 1326.36725,
            "y": 2458.2345
        }
    },
    {
        "data": {
            "id": "72",
            "label": "72",
            "function": "nseq"
        },
        "position": {
            "x": 1326.36725,
            "y": 2493.1136
        }
    },
    {
        "data": {
            "id": "74",
            "label": "74",
            "function": "nseq"
        },
        "position": {
            "x": 1103.0949,
            "y": 2528.0523500000004
        }
    },
    {
        "data": {
            "id": "70",
            "label": "70",
            "function": "nseq"
        },
        "position": {
            "x": 1559.4615000000001,
            "y": 2562.991
        }
    },
    {
        "data": {
            "id": "73",
            "label": "73",
            "function": "nseq"
        },
        "position": {
            "x": 1316.563,
            "y": 2597.87025
        }
    },
    {
        "data": {
            "id": "76",
            "label": "76",
            "function": "nseq"
        },
        "position": {
            "x": 1287.1149,
            "y": 2632.8089999999997
        }
    },
    {
        "data": {
            "id": "77",
            "label": "77",
            "function": "nseq"
        },
        "position": {
            "x": 1343.5556000000001,
            "y": 2667.6879999999996
        }
    },
    {
        "data": {
            "id": "78",
            "label": "78",
            "function": "nseq"
        },
        "position": {
            "x": 1461.3129,
            "y": 2702.6270000000004
        }
    },
    {
        "data": {
            "id": "75",
            "label": "75",
            "function": "nseq"
        },
        "position": {
            "x": 1147.2583,
            "y": 2737.5060000000003
        }
    },
    {
        "data": {
            "id": "79",
            "label": "79",
            "function": "nseq"
        },
        "position": {
            "x": 720.3575,
            "y": 2772.445
        }
    },
    {
        "data": {
            "id": "80",
            "label": "80",
            "function": "nseq"
        },
        "position": {
            "x": 1034.4121,
            "y": 2807.324
        }
    },
    {
        "data": {
            "id": "81",
            "label": "81",
            "function": "nseq"
        },
        "position": {
            "x": 943.6298,
            "y": 2842.2627
        }
    },
    {
        "data": {
            "id": "82",
            "label": "82",
            "function": "nseq"
        },
        "position": {
            "x": 1223.3253,
            "y": 2877.20175
        }
    },
    {
        "data": {
            "id": "83",
            "label": "83",
            "function": "nseq"
        },
        "position": {
            "x": 681.1052,
            "y": 4936.9985
        }
    },
    {
        "data": {
            "id": "85",
            "label": "85",
            "function": "nseq"
        },
        "position": {
            "x": 1004.9639000000001,
            "y": 2912.0805
        }
    },
    {
        "data": {
            "id": "86",
            "label": "86",
            "function": "nseq"
        },
        "position": {
            "x": 1004.9639000000001,
            "y": 2947.0193500000005
        }
    },
    {
        "data": {
            "id": "84",
            "label": "84",
            "function": "nseq"
        },
        "position": {
            "x": 948.5231500000001,
            "y": 2981.8985
        }
    },
    {
        "data": {
            "id": "87",
            "label": "87",
            "function": "nseq"
        },
        "position": {
            "x": 1066.2980499999999,
            "y": 3016.8374999999996
        }
    },
    {
        "data": {
            "id": "88",
            "label": "88",
            "function": "nseq"
        },
        "position": {
            "x": 1279.7484000000002,
            "y": 3051.7165
        }
    },
    {
        "data": {
            "id": "89",
            "label": "89",
            "function": "nseq"
        },
        "position": {
            "x": 1166.9022,
            "y": 3086.6555000000003
        }
    },
    {
        "data": {
            "id": "90",
            "label": "90",
            "function": "nseq"
        },
        "position": {
            "x": 1166.9022,
            "y": 3121.5345
        }
    },
    {
        "data": {
            "id": "91",
            "label": "91",
            "function": "nseq"
        },
        "position": {
            "x": 1407.34525,
            "y": 3156.4730000000004
        }
    },
    {
        "data": {
            "id": "92",
            "label": "92",
            "function": "nseq"
        },
        "position": {
            "x": 1083.4687,
            "y": 3191.4118000000003
        }
    },
    {
        "data": {
            "id": "93",
            "label": "93",
            "function": "nseq"
        },
        "position": {
            "x": 1407.34525,
            "y": 3226.291
        }
    },
    {
        "data": {
            "id": "94",
            "label": "94",
            "function": "nseq"
        },
        "position": {
            "x": 1198.78815,
            "y": 3296.109
        }
    },
    {
        "data": {
            "id": "95",
            "label": "95",
            "function": "nseq"
        },
        "position": {
            "x": 1493.2165,
            "y": 3331.048
        }
    },
    {
        "data": {
            "id": "96",
            "label": "96",
            "function": "nseq"
        },
        "position": {
            "x": 1407.34525,
            "y": 3261.2297000000003
        }
    },
    {
        "data": {
            "id": "97",
            "label": "97",
            "function": "nseq"
        },
        "position": {
            "x": 1507.93165,
            "y": 3365.927
        }
    },
    {
        "data": {
            "id": "98",
            "label": "98",
            "function": "nseq"
        },
        "position": {
            "x": 1490.7609,
            "y": 4971.9113
        }
    },
    {
        "data": {
            "id": "99",
            "label": "99",
            "function": "nseq"
        },
        "position": {
            "x": 1603.6248,
            "y": 3400.8655
        }
    },
    {
        "data": {
            "id": "100",
            "label": "100",
            "function": "nseq"
        },
        "position": {
            "x": 1927.4661,
            "y": 3435.7445
        }
    },
    {
        "data": {
            "id": "101",
            "label": "101",
            "function": "nseq"
        },
        "position": {
            "x": 1853.8015999999998,
            "y": 3470.6837
        }
    },
    {
        "data": {
            "id": "102",
            "label": "102",
            "function": "nseq"
        },
        "position": {
            "x": 1760.7051000000001,
            "y": 3505.6225000000004
        }
    },
    {
        "data": {
            "id": "103",
            "label": "103",
            "function": "nseq"
        },
        "position": {
            "x": 1969.15625,
            "y": 3540.5015000000003
        }
    },
    {
        "data": {
            "id": "104",
            "label": "104",
            "function": "nseq"
        },
        "position": {
            "x": 1947.0745,
            "y": 3610.3195
        }
    },
    {
        "data": {
            "id": "105",
            "label": "105",
            "function": "nseq"
        },
        "position": {
            "x": 2170.3645,
            "y": 3575.44035
        }
    },
    {
        "data": {
            "id": "106",
            "label": "106",
            "function": "nseq"
        },
        "position": {
            "x": 2114.0121,
            "y": 3645.2580000000003
        }
    },
    {
        "data": {
            "id": "107",
            "label": "107",
            "function": "nseq"
        },
        "position": {
            "x": 2172.8377,
            "y": 3680.1375
        }
    },
    {
        "data": {
            "id": "108",
            "label": "108",
            "function": "nseq"
        },
        "position": {
            "x": 2167.8914,
            "y": 3715.076
        }
    },
    {
        "data": {
            "id": "109",
            "label": "109",
            "function": "nseq"
        },
        "position": {
            "x": 3318.612,
            "y": 3749.9553
        }
    },
    {
        "data": {
            "id": "110",
            "label": "110",
            "function": "nseq"
        },
        "position": {
            "x": 3745.5834999999997,
            "y": 4936.9985
        }
    },
    {
        "data": {
            "id": "111",
            "label": "111",
            "function": "nseq"
        },
        "position": {
            "x": 3318.612,
            "y": 3784.894
        }
    },
    {
        "data": {
            "id": "112",
            "label": "112",
            "function": "nseq"
        },
        "position": {
            "x": 3318.612,
            "y": 3819.8327999999997
        }
    },
    {
        "data": {
            "id": "113",
            "label": "113",
            "function": "nseq"
        },
        "position": {
            "x": 2899.06025,
            "y": 3854.712
        }
    },
    {
        "data": {
            "id": "114",
            "label": "114",
            "function": "nseq"
        },
        "position": {
            "x": 3161.56715,
            "y": 3889.6504999999997
        }
    },
    {
        "data": {
            "id": "115",
            "label": "115",
            "function": "nseq"
        },
        "position": {
            "x": 3102.7415,
            "y": 3924.5299999999997
        }
    },
    {
        "data": {
            "id": "116",
            "label": "116",
            "function": "nseq"
        },
        "position": {
            "x": 3105.21485,
            "y": 3959.4685
        }
    },
    {
        "data": {
            "id": "117",
            "label": "117",
            "function": "nseq"
        },
        "position": {
            "x": 2764.0969999999998,
            "y": 3994.3477500000004
        }
    },
    {
        "data": {
            "id": "118",
            "label": "118",
            "function": "nseq"
        },
        "position": {
            "x": 3063.5245,
            "y": 4029.2865
        }
    },
    {
        "data": {
            "id": "119",
            "label": "119",
            "function": "nseq"
        },
        "position": {
            "x": 2729.826,
            "y": 4099.1044999999995
        }
    },
    {
        "data": {
            "id": "120",
            "label": "120",
            "function": "nseq"
        },
        "position": {
            "x": 2967.7785,
            "y": 4064.16565
        }
    },
    {
        "data": {
            "id": "121",
            "label": "121",
            "function": "nseq"
        },
        "position": {
            "x": 2967.7785,
            "y": 4168.922500000001
        }
    },
    {
        "data": {
            "id": "122",
            "label": "122",
            "function": "nseq"
        },
        "position": {
            "x": 2908.9525,
            "y": 4203.861
        }
    },
    {
        "data": {
            "id": "123",
            "label": "123",
            "function": "nseq"
        },
        "position": {
            "x": 3078.1868,
            "y": 4238.7402
        }
    },
    {
        "data": {
            "id": "124",
            "label": "124",
            "function": "nseq"
        },
        "position": {
            "x": 2832.815,
            "y": 4273.679
        }
    },
    {
        "data": {
            "id": "125",
            "label": "125",
            "function": "nseq"
        },
        "position": {
            "x": 2967.7785,
            "y": 4134.043
        }
    },
    {
        "data": {
            "id": "126",
            "label": "126",
            "function": "nseq"
        },
        "position": {
            "x": 3259.7864999999997,
            "y": 4308.558
        }
    },
    {
        "data": {
            "id": "127",
            "label": "127",
            "function": "nseq"
        },
        "position": {
            "x": 2926.088,
            "y": 4343.497
        }
    },
    {
        "data": {
            "id": "128",
            "label": "128",
            "function": "nseq"
        },
        "position": {
            "x": 2999.7525,
            "y": 4378.3763
        }
    },
    {
        "data": {
            "id": "129",
            "label": "129",
            "function": "nseq"
        },
        "position": {
            "x": 2383.762,
            "y": 4413.315
        }
    },
    {
        "data": {
            "id": "130",
            "label": "130",
            "function": "nseq"
        },
        "position": {
            "x": 2271.0569,
            "y": 4448.2300000000005
        }
    },
    {
        "data": {
            "id": "131",
            "label": "131",
            "function": "nseq"
        },
        "position": {
            "x": 2317.517,
            "y": 4483.1385
        }
    },
    {
        "data": {
            "id": "132",
            "label": "132",
            "function": "nseq"
        },
        "position": {
            "x": 2271.0569,
            "y": 4518.0535
        }
    },
    {
        "data": {
            "id": "133",
            "label": "133",
            "function": "nseq"
        },
        "position": {
            "x": 2356.9105,
            "y": 4552.9628
        }
    },
    {
        "data": {
            "id": "134",
            "label": "134",
            "function": "nseq"
        },
        "position": {
            "x": 2180.25715,
            "y": 4587.8775
        }
    },
    {
        "data": {
            "id": "135",
            "label": "135",
            "function": "nseq"
        },
        "position": {
            "x": 2962.8321499999997,
            "y": 4622.78635
        }
    },
    {
        "data": {
            "id": "136",
            "label": "136",
            "function": "nseq"
        },
        "position": {
            "x": 2506.5359999999996,
            "y": 4657.7015
        }
    },
    {
        "data": {
            "id": "137",
            "label": "137",
            "function": "nseq"
        },
        "position": {
            "x": 2459.8995,
            "y": 4692.6105
        }
    },
    {
        "data": {
            "id": "138",
            "label": "138",
            "function": "nseq"
        },
        "position": {
            "x": 2734.77225,
            "y": 4727.525000000001
        }
    },
    {
        "data": {
            "id": "139",
            "label": "139",
            "function": "nseq"
        },
        "position": {
            "x": 2815.6795,
            "y": 4762.4403
        }
    },
    {
        "data": {
            "id": "140",
            "label": "140",
            "function": "nseq"
        },
        "position": {
            "x": 2592.3895,
            "y": 4797.34925
        }
    },
    {
        "data": {
            "id": "141",
            "label": "141",
            "function": "nseq"
        },
        "position": {
            "x": 2815.6795,
            "y": 4832.264
        }
    },
    {
        "data": {
            "id": "142",
            "label": "142",
            "function": "nseq"
        },
        "position": {
            "x": 2926.088,
            "y": 4867.173
        }
    },
    {
        "data": {
            "id": "143",
            "label": "143",
            "function": "nseq"
        },
        "position": {
            "x": 2926.088,
            "y": 4902.088
        }
    },
    {
        "data": {
            "id": "144",
            "label": "144",
            "function": "nseq"
        },
        "position": {
            "x": 3944.3185,
            "y": 2912.0805
        }
    },
    {
        "data": {
            "id": "145",
            "label": "145",
            "function": "nseq"
        },
        "position": {
            "x": 3824.0175,
            "y": 2947.0193500000005
        }
    },
    {
        "data": {
            "id": "146",
            "label": "146",
            "function": "nseq"
        },
        "position": {
            "x": 3524.7665,
            "y": 3051.7165
        }
    },
    {
        "data": {
            "id": "147",
            "label": "147",
            "function": "nseq"
        },
        "position": {
            "x": 1964.21,
            "y": 328.5794
        }
    },
    {
        "data": {
            "id": "148",
            "label": "148",
            "function": "nseq"
        },
        "position": {
            "x": 1969.15625,
            "y": 293.64072
        }
    },
    {
        "data": {
            "id": "149",
            "label": "149",
            "function": "nseq"
        },
        "position": {
            "x": 3821.5445,
            "y": 3016.8374999999996
        }
    },
    {
        "data": {
            "id": -5,
            "label": "S",
            "function": "nseq"
        },
        "position": {
            "x": 4743.499,
            "y": 0.00014551914999999998
        }
    },
    {
        "data": {
            "id": -7,
            "label": "F",
            "function": "nseq"
        },
        "position": {
            "x": 3418.598,
            "y": 4992.249000000001
        }
    },
    {
        "data": {
            "source": "0",
            "target": "1"
        }
    },
    {
        "data": {
            "source": "0",
            "target": "2"
        }
    },
    {
        "data": {
            "source": "0",
            "target": "4"
        }
    },
    {
        "data": {
            "source": "28",
            "target": "27"
        }
    },
    {
        "data": {
            "source": "28",
            "target": "29"
        }
    },
    {
        "data": {
            "source": "28",
            "target": "30"
        }
    },
    {
        "data": {
            "source": "53",
            "target": "54"
        }
    },
    {
        "data": {
            "source": "28",
            "target": "31"
        }
    },
    {
        "data": {
            "source": "28",
            "target": "32"
        }
    },
    {
        "data": {
            "source": "81",
            "target": "82"
        }
    },
    {
        "data": {
            "source": "53",
            "target": "57"
        }
    },
    {
        "data": {
            "source": "81",
            "target": "83"
        }
    },
    {
        "data": {
            "source": "108",
            "target": "109"
        }
    },
    {
        "data": {
            "source": "28",
            "target": "35"
        }
    },
    {
        "data": {
            "source": "108",
            "target": "110"
        }
    },
    {
        "data": {
            "source": "135",
            "target": "136"
        }
    },
    {
        "data": {
            "source": "135",
            "target": "137"
        }
    },
    {
        "data": {
            "source": "82",
            "target": "63"
        }
    },
    {
        "data": {
            "source": "108",
            "target": "129"
        }
    },
    {
        "data": {
            "source": "82",
            "target": "76"
        }
    },
    {
        "data": {
            "source": "1",
            "target": "2"
        }
    },
    {
        "data": {
            "source": "1",
            "target": "4"
        }
    },
    {
        "data": {
            "source": "27",
            "target": "29"
        }
    },
    {
        "data": {
            "source": "27",
            "target": "30"
        }
    },
    {
        "data": {
            "source": "27",
            "target": "31"
        }
    },
    {
        "data": {
            "source": "54",
            "target": "55"
        }
    },
    {
        "data": {
            "source": "54",
            "target": "56"
        }
    },
    {
        "data": {
            "source": "54",
            "target": "57"
        }
    },
    {
        "data": {
            "source": "82",
            "target": "83"
        }
    },
    {
        "data": {
            "source": "82",
            "target": "85"
        }
    },
    {
        "data": {
            "source": "109",
            "target": "111"
        }
    },
    {
        "data": {
            "source": "109",
            "target": "112"
        }
    },
    {
        "data": {
            "source": "136",
            "target": "137"
        }
    },
    {
        "data": {
            "source": "136",
            "target": "138"
        }
    },
    {
        "data": {
            "source": "109",
            "target": "114"
        }
    },
    {
        "data": {
            "source": "28",
            "target": "79"
        }
    },
    {
        "data": {
            "source": "2",
            "target": "4"
        }
    },
    {
        "data": {
            "source": "2",
            "target": "5"
        }
    },
    {
        "data": {
            "source": "2",
            "target": "3"
        }
    },
    {
        "data": {
            "source": "29",
            "target": "30"
        }
    },
    {
        "data": {
            "source": "2",
            "target": "7"
        }
    },
    {
        "data": {
            "source": "29",
            "target": "31"
        }
    },
    {
        "data": {
            "source": "29",
            "target": "32"
        }
    },
    {
        "data": {
            "source": "55",
            "target": "56"
        }
    },
    {
        "data": {
            "source": "83",
            "target": "85"
        }
    },
    {
        "data": {
            "source": "110",
            "target": "109"
        }
    },
    {
        "data": {
            "source": "83",
            "target": "86"
        }
    },
    {
        "data": {
            "source": "83",
            "target": "84"
        }
    },
    {
        "data": {
            "source": "110",
            "target": "111"
        }
    },
    {
        "data": {
            "source": "137",
            "target": "138"
        }
    },
    {
        "data": {
            "source": "137",
            "target": "140"
        }
    },
    {
        "data": {
            "source": "82",
            "target": "129"
        }
    },
    {
        "data": {
            "source": "83",
            "target": "98"
        }
    },
    {
        "data": {
            "source": "82",
            "target": "144"
        }
    },
    {
        "data": {
            "source": "56",
            "target": "59"
        }
    },
    {
        "data": {
            "source": "4",
            "target": "5"
        }
    },
    {
        "data": {
            "source": "30",
            "target": "31"
        }
    },
    {
        "data": {
            "source": "30",
            "target": "32"
        }
    },
    {
        "data": {
            "source": "56",
            "target": "57"
        }
    },
    {
        "data": {
            "source": "56",
            "target": "58"
        }
    },
    {
        "data": {
            "source": "56",
            "target": "63"
        }
    },
    {
        "data": {
            "source": "85",
            "target": "86"
        }
    },
    {
        "data": {
            "source": "111",
            "target": "112"
        }
    },
    {
        "data": {
            "source": "111",
            "target": "113"
        }
    },
    {
        "data": {
            "source": "138",
            "target": "139"
        }
    },
    {
        "data": {
            "source": "138",
            "target": "140"
        }
    },
    {
        "data": {
            "source": "83",
            "target": "129"
        }
    },
    {
        "data": {
            "source": "83",
            "target": "135"
        }
    },
    {
        "data": {
            "source": "5",
            "target": "3"
        }
    },
    {
        "data": {
            "source": "5",
            "target": "7"
        }
    },
    {
        "data": {
            "source": "31",
            "target": "32"
        }
    },
    {
        "data": {
            "source": "5",
            "target": "13"
        }
    },
    {
        "data": {
            "source": "31",
            "target": "33"
        }
    },
    {
        "data": {
            "source": "57",
            "target": "58"
        }
    },
    {
        "data": {
            "source": "31",
            "target": "35"
        }
    },
    {
        "data": {
            "source": "57",
            "target": "63"
        }
    },
    {
        "data": {
            "source": "139",
            "target": "135"
        }
    },
    {
        "data": {
            "source": "86",
            "target": "84"
        }
    },
    {
        "data": {
            "source": "86",
            "target": "87"
        }
    },
    {
        "data": {
            "source": "112",
            "target": "113"
        }
    },
    {
        "data": {
            "source": "139",
            "target": "140"
        }
    },
    {
        "data": {
            "source": "86",
            "target": "91"
        }
    },
    {
        "data": {
            "source": "139",
            "target": "141"
        }
    },
    {
        "data": {
            "source": "112",
            "target": "118"
        }
    },
    {
        "data": {
            "source": "58",
            "target": "59"
        }
    },
    {
        "data": {
            "source": "3",
            "target": "4"
        }
    },
    {
        "data": {
            "source": "3",
            "target": "7"
        }
    },
    {
        "data": {
            "source": "3",
            "target": "13"
        }
    },
    {
        "data": {
            "source": "32",
            "target": "33"
        }
    },
    {
        "data": {
            "source": "32",
            "target": "34"
        }
    },
    {
        "data": {
            "source": "58",
            "target": "63"
        }
    },
    {
        "data": {
            "source": "58",
            "target": "60"
        }
    },
    {
        "data": {
            "source": "84",
            "target": "87"
        }
    },
    {
        "data": {
            "source": "113",
            "target": "114"
        }
    },
    {
        "data": {
            "source": "113",
            "target": "115"
        }
    },
    {
        "data": {
            "source": "113",
            "target": "116"
        }
    },
    {
        "data": {
            "source": "140",
            "target": "141"
        }
    },
    {
        "data": {
            "source": "113",
            "target": "117"
        }
    },
    {
        "data": {
            "source": "140",
            "target": "142"
        }
    },
    {
        "data": {
            "source": "113",
            "target": "118"
        }
    },
    {
        "data": {
            "source": "140",
            "target": "143"
        }
    },
    {
        "data": {
            "source": "144",
            "target": "4"
        }
    },
    {
        "data": {
            "source": "58",
            "target": "79"
        }
    },
    {
        "data": {
            "source": "144",
            "target": "6"
        }
    },
    {
        "data": {
            "source": "5",
            "target": "79"
        }
    },
    {
        "data": {
            "source": "7",
            "target": "13"
        }
    },
    {
        "data": {
            "source": "33",
            "target": "34"
        }
    },
    {
        "data": {
            "source": "33",
            "target": "35"
        }
    },
    {
        "data": {
            "source": "63",
            "target": "60"
        }
    },
    {
        "data": {
            "source": "63",
            "target": "61"
        }
    },
    {
        "data": {
            "source": "87",
            "target": "88"
        }
    },
    {
        "data": {
            "source": "63",
            "target": "65"
        }
    },
    {
        "data": {
            "source": "87",
            "target": "89"
        }
    },
    {
        "data": {
            "source": "114",
            "target": "115"
        }
    },
    {
        "data": {
            "source": "114",
            "target": "116"
        }
    },
    {
        "data": {
            "source": "114",
            "target": "117"
        }
    },
    {
        "data": {
            "source": "141",
            "target": "142"
        }
    },
    {
        "data": {
            "source": "63",
            "target": "64"
        }
    },
    {
        "data": {
            "source": "114",
            "target": "118"
        }
    },
    {
        "data": {
            "source": "145",
            "target": "4"
        }
    },
    {
        "data": {
            "source": "145",
            "target": "6"
        }
    },
    {
        "data": {
            "source": "143",
            "target": "83"
        }
    },
    {
        "data": {
            "source": "6",
            "target": "0"
        }
    },
    {
        "data": {
            "source": "6",
            "target": "1"
        }
    },
    {
        "data": {
            "source": "6",
            "target": "2"
        }
    },
    {
        "data": {
            "source": "6",
            "target": "4"
        }
    },
    {
        "data": {
            "source": "34",
            "target": "35"
        }
    },
    {
        "data": {
            "source": "142",
            "target": "135"
        }
    },
    {
        "data": {
            "source": "34",
            "target": "36"
        }
    },
    {
        "data": {
            "source": "60",
            "target": "61"
        }
    },
    {
        "data": {
            "source": "60",
            "target": "62"
        }
    },
    {
        "data": {
            "source": "60",
            "target": "65"
        }
    },
    {
        "data": {
            "source": "88",
            "target": "89"
        }
    },
    {
        "data": {
            "source": "142",
            "target": "139"
        }
    },
    {
        "data": {
            "source": "88",
            "target": "91"
        }
    },
    {
        "data": {
            "source": "115",
            "target": "116"
        }
    },
    {
        "data": {
            "source": "115",
            "target": "117"
        }
    },
    {
        "data": {
            "source": "115",
            "target": "118"
        }
    },
    {
        "data": {
            "source": "142",
            "target": "143"
        }
    },
    {
        "data": {
            "source": "143",
            "target": "110"
        }
    },
    {
        "data": {
            "source": "146",
            "target": "0"
        }
    },
    {
        "data": {
            "source": "146",
            "target": "1"
        }
    },
    {
        "data": {
            "source": "146",
            "target": "2"
        }
    },
    {
        "data": {
            "source": "146",
            "target": "4"
        }
    },
    {
        "data": {
            "source": "13",
            "target": "8"
        }
    },
    {
        "data": {
            "source": "13",
            "target": "9"
        }
    },
    {
        "data": {
            "source": "143",
            "target": "135"
        }
    },
    {
        "data": {
            "source": "13",
            "target": "10"
        }
    },
    {
        "data": {
            "source": "35",
            "target": "36"
        }
    },
    {
        "data": {
            "source": "35",
            "target": "37"
        }
    },
    {
        "data": {
            "source": "61",
            "target": "62"
        }
    },
    {
        "data": {
            "source": "13",
            "target": "14"
        }
    },
    {
        "data": {
            "source": "61",
            "target": "65"
        }
    },
    {
        "data": {
            "source": "13",
            "target": "15"
        }
    },
    {
        "data": {
            "source": "89",
            "target": "90"
        }
    },
    {
        "data": {
            "source": "116",
            "target": "117"
        }
    },
    {
        "data": {
            "source": "116",
            "target": "118"
        }
    },
    {
        "data": {
            "source": "147",
            "target": "8"
        }
    },
    {
        "data": {
            "source": "147",
            "target": "9"
        }
    },
    {
        "data": {
            "source": "147",
            "target": "10"
        }
    },
    {
        "data": {
            "source": "8",
            "target": "9"
        }
    },
    {
        "data": {
            "source": "8",
            "target": "10"
        }
    },
    {
        "data": {
            "source": "8",
            "target": "11"
        }
    },
    {
        "data": {
            "source": "36",
            "target": "37"
        }
    },
    {
        "data": {
            "source": "36",
            "target": "38"
        }
    },
    {
        "data": {
            "source": "8",
            "target": "14"
        }
    },
    {
        "data": {
            "source": "62",
            "target": "65"
        }
    },
    {
        "data": {
            "source": "8",
            "target": "15"
        }
    },
    {
        "data": {
            "source": "62",
            "target": "66"
        }
    },
    {
        "data": {
            "source": "90",
            "target": "91"
        }
    },
    {
        "data": {
            "source": "35",
            "target": "79"
        }
    },
    {
        "data": {
            "source": "90",
            "target": "92"
        }
    },
    {
        "data": {
            "source": "62",
            "target": "64"
        }
    },
    {
        "data": {
            "source": "90",
            "target": "93"
        }
    },
    {
        "data": {
            "source": "117",
            "target": "118"
        }
    },
    {
        "data": {
            "source": "117",
            "target": "119"
        }
    },
    {
        "data": {
            "source": "144",
            "target": "145"
        }
    },
    {
        "data": {
            "source": "144",
            "target": "149"
        }
    },
    {
        "data": {
            "source": "148",
            "target": "8"
        }
    },
    {
        "data": {
            "source": "148",
            "target": "9"
        }
    },
    {
        "data": {
            "source": "7",
            "target": "147"
        }
    },
    {
        "data": {
            "source": "7",
            "target": "148"
        }
    },
    {
        "data": {
            "source": "13",
            "target": "79"
        }
    },
    {
        "data": {
            "source": "9",
            "target": "10"
        }
    },
    {
        "data": {
            "source": "9",
            "target": "11"
        }
    },
    {
        "data": {
            "source": "9",
            "target": "12"
        }
    },
    {
        "data": {
            "source": "37",
            "target": "38"
        }
    },
    {
        "data": {
            "source": "37",
            "target": "39"
        }
    },
    {
        "data": {
            "source": "65",
            "target": "66"
        }
    },
    {
        "data": {
            "source": "65",
            "target": "67"
        }
    },
    {
        "data": {
            "source": "91",
            "target": "92"
        }
    },
    {
        "data": {
            "source": "91",
            "target": "93"
        }
    },
    {
        "data": {
            "source": "118",
            "target": "119"
        }
    },
    {
        "data": {
            "source": "118",
            "target": "120"
        }
    },
    {
        "data": {
            "source": "145",
            "target": "146"
        }
    },
    {
        "data": {
            "source": "149",
            "target": "0"
        }
    },
    {
        "data": {
            "source": "145",
            "target": "149"
        }
    },
    {
        "data": {
            "source": "149",
            "target": "1"
        }
    },
    {
        "data": {
            "source": "149",
            "target": "4"
        }
    },
    {
        "data": {
            "source": "6",
            "target": "146"
        }
    },
    {
        "data": {
            "source": "6",
            "target": "149"
        }
    },
    {
        "data": {
            "source": "10",
            "target": "11"
        }
    },
    {
        "data": {
            "source": "10",
            "target": "12"
        }
    },
    {
        "data": {
            "source": "10",
            "target": "14"
        }
    },
    {
        "data": {
            "source": "38",
            "target": "39"
        }
    },
    {
        "data": {
            "source": "66",
            "target": "67"
        }
    },
    {
        "data": {
            "source": "66",
            "target": "68"
        }
    },
    {
        "data": {
            "source": "92",
            "target": "93"
        }
    },
    {
        "data": {
            "source": "92",
            "target": "96"
        }
    },
    {
        "data": {
            "source": "119",
            "target": "121"
        }
    },
    {
        "data": {
            "source": "119",
            "target": "124"
        }
    },
    {
        "data": {
            "source": "119",
            "target": "125"
        }
    },
    {
        "data": {
            "source": "13",
            "target": "147"
        }
    },
    {
        "data": {
            "source": "13",
            "target": "148"
        }
    },
    {
        "data": {
            "source": "11",
            "target": "12"
        }
    },
    {
        "data": {
            "source": "11",
            "target": "14"
        }
    },
    {
        "data": {
            "source": "11",
            "target": "15"
        }
    },
    {
        "data": {
            "source": "39",
            "target": "41"
        }
    },
    {
        "data": {
            "source": "39",
            "target": "40"
        }
    },
    {
        "data": {
            "source": "67",
            "target": "68"
        }
    },
    {
        "data": {
            "source": "120",
            "target": "117"
        }
    },
    {
        "data": {
            "source": "67",
            "target": "64"
        }
    },
    {
        "data": {
            "source": "93",
            "target": "94"
        }
    },
    {
        "data": {
            "source": "120",
            "target": "119"
        }
    },
    {
        "data": {
            "source": "93",
            "target": "95"
        }
    },
    {
        "data": {
            "source": "93",
            "target": "96"
        }
    },
    {
        "data": {
            "source": "120",
            "target": "121"
        }
    },
    {
        "data": {
            "source": "120",
            "target": "125"
        }
    },
    {
        "data": {
            "source": "12",
            "target": "14"
        }
    },
    {
        "data": {
            "source": "12",
            "target": "15"
        }
    },
    {
        "data": {
            "source": "41",
            "target": "40"
        }
    },
    {
        "data": {
            "source": "41",
            "target": "42"
        }
    },
    {
        "data": {
            "source": "41",
            "target": "43"
        }
    },
    {
        "data": {
            "source": "68",
            "target": "64"
        }
    },
    {
        "data": {
            "source": "68",
            "target": "69"
        }
    },
    {
        "data": {
            "source": "68",
            "target": "71"
        }
    },
    {
        "data": {
            "source": "94",
            "target": "95"
        }
    },
    {
        "data": {
            "source": "121",
            "target": "122"
        }
    },
    {
        "data": {
            "source": "148",
            "target": "147"
        }
    },
    {
        "data": {
            "source": "68",
            "target": "70"
        }
    },
    {
        "data": {
            "source": "94",
            "target": "98"
        }
    },
    {
        "data": {
            "source": "121",
            "target": "123"
        }
    },
    {
        "data": {
            "source": "121",
            "target": "124"
        }
    },
    {
        "data": {
            "source": "64",
            "target": "65"
        }
    },
    {
        "data": {
            "source": "14",
            "target": "15"
        }
    },
    {
        "data": {
            "source": "40",
            "target": "42"
        }
    },
    {
        "data": {
            "source": "14",
            "target": "19"
        }
    },
    {
        "data": {
            "source": "40",
            "target": "43"
        }
    },
    {
        "data": {
            "source": "64",
            "target": "69"
        }
    },
    {
        "data": {
            "source": "64",
            "target": "71"
        }
    },
    {
        "data": {
            "source": "149",
            "target": "146"
        }
    },
    {
        "data": {
            "source": "95",
            "target": "97"
        }
    },
    {
        "data": {
            "source": "95",
            "target": "98"
        }
    },
    {
        "data": {
            "source": "122",
            "target": "123"
        }
    },
    {
        "data": {
            "source": "122",
            "target": "124"
        }
    },
    {
        "data": {
            "source": "12",
            "target": "79"
        }
    },
    {
        "data": {
            "source": "15",
            "target": "16"
        }
    },
    {
        "data": {
            "source": "15",
            "target": "17"
        }
    },
    {
        "data": {
            "source": "42",
            "target": "43"
        }
    },
    {
        "data": {
            "source": "42",
            "target": "44"
        }
    },
    {
        "data": {
            "source": "96",
            "target": "94"
        }
    },
    {
        "data": {
            "source": "69",
            "target": "71"
        }
    },
    {
        "data": {
            "source": "96",
            "target": "95"
        }
    },
    {
        "data": {
            "source": "69",
            "target": "72"
        }
    },
    {
        "data": {
            "source": "96",
            "target": "97"
        }
    },
    {
        "data": {
            "source": "69",
            "target": "70"
        }
    },
    {
        "data": {
            "source": "96",
            "target": "98"
        }
    },
    {
        "data": {
            "source": "123",
            "target": "124"
        }
    },
    {
        "data": {
            "source": "123",
            "target": "126"
        }
    },
    {
        "data": {
            "source": "123",
            "target": "127"
        }
    },
    {
        "data": {
            "source": "16",
            "target": "17"
        }
    },
    {
        "data": {
            "source": "16",
            "target": "19"
        }
    },
    {
        "data": {
            "source": "43",
            "target": "44"
        }
    },
    {
        "data": {
            "source": "43",
            "target": "45"
        }
    },
    {
        "data": {
            "source": "43",
            "target": "46"
        }
    },
    {
        "data": {
            "source": "71",
            "target": "72"
        }
    },
    {
        "data": {
            "source": "43",
            "target": "51"
        }
    },
    {
        "data": {
            "source": "71",
            "target": "74"
        }
    },
    {
        "data": {
            "source": "97",
            "target": "99"
        }
    },
    {
        "data": {
            "source": "97",
            "target": "100"
        }
    },
    {
        "data": {
            "source": "124",
            "target": "126"
        }
    },
    {
        "data": {
            "source": "43",
            "target": "49"
        }
    },
    {
        "data": {
            "source": "97",
            "target": "102"
        }
    },
    {
        "data": {
            "source": "124",
            "target": "127"
        }
    },
    {
        "data": {
            "source": "124",
            "target": "129"
        }
    },
    {
        "data": {
            "source": "124",
            "target": "135"
        }
    },
    {
        "data": {
            "source": "17",
            "target": "19"
        }
    },
    {
        "data": {
            "source": "17",
            "target": "21"
        }
    },
    {
        "data": {
            "source": "44",
            "target": "45"
        }
    },
    {
        "data": {
            "source": "44",
            "target": "46"
        }
    },
    {
        "data": {
            "source": "125",
            "target": "121"
        }
    },
    {
        "data": {
            "source": "17",
            "target": "18"
        }
    },
    {
        "data": {
            "source": "44",
            "target": "51"
        }
    },
    {
        "data": {
            "source": "72",
            "target": "74"
        }
    },
    {
        "data": {
            "source": "98",
            "target": "97"
        }
    },
    {
        "data": {
            "source": "125",
            "target": "122"
        }
    },
    {
        "data": {
            "source": "125",
            "target": "123"
        }
    },
    {
        "data": {
            "source": "72",
            "target": "73"
        }
    },
    {
        "data": {
            "source": "98",
            "target": "99"
        }
    },
    {
        "data": {
            "source": "98",
            "target": "100"
        }
    },
    {
        "data": {
            "source": "125",
            "target": "126"
        }
    },
    {
        "data": {
            "source": "98",
            "target": "102"
        }
    },
    {
        "data": {
            "source": "125",
            "target": "127"
        }
    },
    {
        "data": {
            "source": "98",
            "target": "103"
        }
    },
    {
        "data": {
            "source": "19",
            "target": "21"
        }
    },
    {
        "data": {
            "source": "19",
            "target": "24"
        }
    },
    {
        "data": {
            "source": "45",
            "target": "46"
        }
    },
    {
        "data": {
            "source": "45",
            "target": "51"
        }
    },
    {
        "data": {
            "source": "19",
            "target": "20"
        }
    },
    {
        "data": {
            "source": "74",
            "target": "70"
        }
    },
    {
        "data": {
            "source": "74",
            "target": "76"
        }
    },
    {
        "data": {
            "source": "99",
            "target": "100"
        }
    },
    {
        "data": {
            "source": "99",
            "target": "101"
        }
    },
    {
        "data": {
            "source": "99",
            "target": "102"
        }
    },
    {
        "data": {
            "source": "126",
            "target": "127"
        }
    },
    {
        "data": {
            "source": "74",
            "target": "75"
        }
    },
    {
        "data": {
            "source": "74",
            "target": "79"
        }
    },
    {
        "data": {
            "source": "126",
            "target": "129"
        }
    },
    {
        "data": {
            "source": "126",
            "target": "135"
        }
    },
    {
        "data": {
            "source": "21",
            "target": "24"
        }
    },
    {
        "data": {
            "source": "70",
            "target": "71"
        }
    },
    {
        "data": {
            "source": "70",
            "target": "72"
        }
    },
    {
        "data": {
            "source": "21",
            "target": "18"
        }
    },
    {
        "data": {
            "source": "46",
            "target": "51"
        }
    },
    {
        "data": {
            "source": "46",
            "target": "52"
        }
    },
    {
        "data": {
            "source": "21",
            "target": "22"
        }
    },
    {
        "data": {
            "source": "70",
            "target": "73"
        }
    },
    {
        "data": {
            "source": "46",
            "target": "47"
        }
    },
    {
        "data": {
            "source": "70",
            "target": "76"
        }
    },
    {
        "data": {
            "source": "46",
            "target": "48"
        }
    },
    {
        "data": {
            "source": "100",
            "target": "101"
        }
    },
    {
        "data": {
            "source": "100",
            "target": "102"
        }
    },
    {
        "data": {
            "source": "100",
            "target": "103"
        }
    },
    {
        "data": {
            "source": "127",
            "target": "128"
        }
    },
    {
        "data": {
            "source": "24",
            "target": "25"
        }
    },
    {
        "data": {
            "source": "24",
            "target": "18"
        }
    },
    {
        "data": {
            "source": "73",
            "target": "74"
        }
    },
    {
        "data": {
            "source": "51",
            "target": "52"
        }
    },
    {
        "data": {
            "source": "51",
            "target": "59"
        }
    },
    {
        "data": {
            "source": "73",
            "target": "76"
        }
    },
    {
        "data": {
            "source": "73",
            "target": "77"
        }
    },
    {
        "data": {
            "source": "128",
            "target": "126"
        }
    },
    {
        "data": {
            "source": "101",
            "target": "102"
        }
    },
    {
        "data": {
            "source": "73",
            "target": "75"
        }
    },
    {
        "data": {
            "source": "101",
            "target": "103"
        }
    },
    {
        "data": {
            "source": "128",
            "target": "129"
        }
    },
    {
        "data": {
            "source": "128",
            "target": "135"
        }
    },
    {
        "data": {
            "source": "25",
            "target": "18"
        }
    },
    {
        "data": {
            "source": "25",
            "target": "20"
        }
    },
    {
        "data": {
            "source": "25",
            "target": "22"
        }
    },
    {
        "data": {
            "source": "52",
            "target": "59"
        }
    },
    {
        "data": {
            "source": "25",
            "target": "23"
        }
    },
    {
        "data": {
            "source": "25",
            "target": "26"
        }
    },
    {
        "data": {
            "source": "76",
            "target": "77"
        }
    },
    {
        "data": {
            "source": "25",
            "target": "28"
        }
    },
    {
        "data": {
            "source": "102",
            "target": "103"
        }
    },
    {
        "data": {
            "source": "52",
            "target": "53"
        }
    },
    {
        "data": {
            "source": "102",
            "target": "104"
        }
    },
    {
        "data": {
            "source": "52",
            "target": "54"
        }
    },
    {
        "data": {
            "source": "102",
            "target": "105"
        }
    },
    {
        "data": {
            "source": "129",
            "target": "130"
        }
    },
    {
        "data": {
            "source": "129",
            "target": "131"
        }
    },
    {
        "data": {
            "source": "129",
            "target": "133"
        }
    },
    {
        "data": {
            "source": "59",
            "target": "40"
        }
    },
    {
        "data": {
            "source": "18",
            "target": "19"
        }
    },
    {
        "data": {
            "source": "18",
            "target": "20"
        }
    },
    {
        "data": {
            "source": "18",
            "target": "22"
        }
    },
    {
        "data": {
            "source": "18",
            "target": "23"
        }
    },
    {
        "data": {
            "source": "59",
            "target": "47"
        }
    },
    {
        "data": {
            "source": "59",
            "target": "48"
        }
    },
    {
        "data": {
            "source": "18",
            "target": "28"
        }
    },
    {
        "data": {
            "source": "59",
            "target": "49"
        }
    },
    {
        "data": {
            "source": "77",
            "target": "78"
        }
    },
    {
        "data": {
            "source": "103",
            "target": "104"
        }
    },
    {
        "data": {
            "source": "103",
            "target": "105"
        }
    },
    {
        "data": {
            "source": "130",
            "target": "131"
        }
    },
    {
        "data": {
            "source": "130",
            "target": "132"
        }
    },
    {
        "data": {
            "source": "59",
            "target": "63"
        }
    },
    {
        "data": {
            "source": "59",
            "target": "60"
        }
    },
    {
        "data": {
            "source": "20",
            "target": "21"
        }
    },
    {
        "data": {
            "source": "78",
            "target": "70"
        }
    },
    {
        "data": {
            "source": "20",
            "target": "22"
        }
    },
    {
        "data": {
            "source": "20",
            "target": "23"
        }
    },
    {
        "data": {
            "source": "20",
            "target": "26"
        }
    },
    {
        "data": {
            "source": "47",
            "target": "48"
        }
    },
    {
        "data": {
            "source": "20",
            "target": "28"
        }
    },
    {
        "data": {
            "source": "47",
            "target": "49"
        }
    },
    {
        "data": {
            "source": "78",
            "target": "75"
        }
    },
    {
        "data": {
            "source": "78",
            "target": "79"
        }
    },
    {
        "data": {
            "source": "104",
            "target": "106"
        }
    },
    {
        "data": {
            "source": "104",
            "target": "107"
        }
    },
    {
        "data": {
            "source": "131",
            "target": "132"
        }
    },
    {
        "data": {
            "source": "78",
            "target": "83"
        }
    },
    {
        "data": {
            "source": "131",
            "target": "133"
        }
    },
    {
        "data": {
            "source": "78",
            "target": "85"
        }
    },
    {
        "data": {
            "source": "22",
            "target": "23"
        }
    },
    {
        "data": {
            "source": "75",
            "target": "76"
        }
    },
    {
        "data": {
            "source": "22",
            "target": "26"
        }
    },
    {
        "data": {
            "source": "75",
            "target": "77"
        }
    },
    {
        "data": {
            "source": "22",
            "target": "28"
        }
    },
    {
        "data": {
            "source": "48",
            "target": "49"
        }
    },
    {
        "data": {
            "source": "48",
            "target": "50"
        }
    },
    {
        "data": {
            "source": "48",
            "target": "53"
        }
    },
    {
        "data": {
            "source": "75",
            "target": "79"
        }
    },
    {
        "data": {
            "source": "105",
            "target": "104"
        }
    },
    {
        "data": {
            "source": "75",
            "target": "80"
        }
    },
    {
        "data": {
            "source": "105",
            "target": "106"
        }
    },
    {
        "data": {
            "source": "105",
            "target": "107"
        }
    },
    {
        "data": {
            "source": "75",
            "target": "83"
        }
    },
    {
        "data": {
            "source": "132",
            "target": "133"
        }
    },
    {
        "data": {
            "source": "75",
            "target": "85"
        }
    },
    {
        "data": {
            "source": "132",
            "target": "134"
        }
    },
    {
        "data": {
            "source": "132",
            "target": "136"
        }
    },
    {
        "data": {
            "source": "23",
            "target": "24"
        }
    },
    {
        "data": {
            "source": "49",
            "target": "51"
        }
    },
    {
        "data": {
            "source": "23",
            "target": "26"
        }
    },
    {
        "data": {
            "source": "23",
            "target": "28"
        }
    },
    {
        "data": {
            "source": "49",
            "target": "50"
        }
    },
    {
        "data": {
            "source": "49",
            "target": "53"
        }
    },
    {
        "data": {
            "source": "49",
            "target": "54"
        }
    },
    {
        "data": {
            "source": "79",
            "target": "80"
        }
    },
    {
        "data": {
            "source": "79",
            "target": "81"
        }
    },
    {
        "data": {
            "source": "79",
            "target": "82"
        }
    },
    {
        "data": {
            "source": "106",
            "target": "107"
        }
    },
    {
        "data": {
            "source": "106",
            "target": "108"
        }
    },
    {
        "data": {
            "source": "133",
            "target": "134"
        }
    },
    {
        "data": {
            "source": "133",
            "target": "136"
        }
    },
    {
        "data": {
            "source": "133",
            "target": "137"
        }
    },
    {
        "data": {
            "source": "50",
            "target": "51"
        }
    },
    {
        "data": {
            "source": "26",
            "target": "28"
        }
    },
    {
        "data": {
            "source": "26",
            "target": "27"
        }
    },
    {
        "data": {
            "source": "50",
            "target": "53"
        }
    },
    {
        "data": {
            "source": "50",
            "target": "54"
        }
    },
    {
        "data": {
            "source": "80",
            "target": "81"
        }
    },
    {
        "data": {
            "source": "80",
            "target": "82"
        }
    },
    {
        "data": {
            "source": "107",
            "target": "108"
        }
    },
    {
        "data": {
            "source": "107",
            "target": "110"
        }
    },
    {
        "data": {
            "source": "134",
            "target": "135"
        }
    },
    {
        "data": {
            "source": "134",
            "target": "136"
        }
    },
    {
        "data": {
            "source": "134",
            "target": "137"
        }
    },
    {
        "data": {
            "source": "82",
            "target": "14"
        }
    },
    {
        "data": {
            "source": "134",
            "target": "143"
        }
    },
    {
        "data": {
            "source": "-5",
            "target": "144"
        }
    },
    {
        "data": {
            "source": "-5",
            "target": "145"
        }
    },
    {
        "data": {
            "source": "-5",
            "target": "4"
        }
    },
    {
        "data": {
            "source": "-5",
            "target": "6"
        }
    },
    {
        "data": {
            "source": "-5",
            "target": "79"
        }
    },
    {
        "data": {
            "source": "128",
            "target": "-7"
        }
    },
    {
        "data": {
            "source": "96",
            "target": "-7"
        }
    },
    {
        "data": {
            "source": "7",
            "target": "-7"
        }
    },
    {
        "data": {
            "source": "135",
            "target": "-7"
        }
    },
    {
        "data": {
            "source": "13",
            "target": "-7"
        }
    },
    {
        "data": {
            "source": "104",
            "target": "-7"
        }
    },
    {
        "data": {
            "source": "42",
            "target": "-7"
        }
    },
    {
        "data": {
            "source": "43",
            "target": "-7"
        }
    },
    {
        "data": {
            "source": "108",
            "target": "-7"
        }
    },
    {
        "data": {
            "source": "142",
            "target": "-7"
        }
    },
    {
        "data": {
            "source": "75",
            "target": "-7"
        }
    },
    {
        "data": {
            "source": "143",
            "target": "-7"
        }
    },
    {
        "data": {
            "source": "83",
            "target": "-7"
        }
    },
    {
        "data": {
            "source": "148",
            "target": "-7"
        }
    },
    {
        "data": {
            "source": "50",
            "target": "-7"
        }
    },
    {
        "data": {
            "source": "119",
            "target": "-7"
        }
    },
    {
        "data": {
            "source": "91",
            "target": "-7"
        }
    },
    {
        "data": {
            "source": "124",
            "target": "-7"
        }
    },
    {
        "data": {
            "source": "93",
            "target": "-7"
        }
    },
    {
        "data": {
            "source": "126",
            "target": "-7"
        }
    },
    {
        "data": {
            "source": "95",
            "target": "-7"
        }
    },
    {
        "data": {
            "sequence": null
        }
    }
]